graphbin2/__init__.py
graphbin2/cli.py
graphbin2/graphbin2_Flye.py
graphbin2/graphbin2_MEGAHIT.py
graphbin2/graphbin2_SGA.py
graphbin2/graphbin2_SPAdes.py
graphbin2/bidirectionalmap/__init__.py
graphbin2/bidirectionalmap/bidirectionalmap.py
graphbin2/support/README.md
graphbin2/support/prepResult.py
graphbin2-1.3.3.dist-info/entry_points.txt
graphbin2-1.3.3.dist-info/LICENSE
graphbin2-1.3.3.dist-info/WHEEL
graphbin2-1.3.3.dist-info/METADATA
graphbin2-1.3.3.dist-info/RECORD
