Metadata-Version: 2.1
Name: graphbin2
Version: 1.3.3
Summary: GraphBin2: Refined and Overlapped Binning of Metagenomic Contigs Using Assembly Graphs
Keywords: metagenomics,binning,contigs,bioinformatics
Author-email: Vijini Mallawaarachchi <viji.mallawaarachchi@gmail.com>
Requires-Python: >=3.9,<3.13
Classifier: Development Status :: 5 - Production/Stable
Classifier: Intended Audience :: Science/Research
Classifier: Programming Language :: Python :: 3
Classifier: License :: OSI Approved :: BSD License
Classifier: Natural Language :: English
Classifier: Topic :: Scientific/Engineering :: Bio-Informatics
Requires-Dist: cogent3
Requires-Dist: python-igraph
Requires-Dist: scipy
Requires-Dist: tqdm
Requires-Dist: click
Requires-Dist: black ; extra == "dev"
Requires-Dist: click ; extra == "dev"
Requires-Dist: docformatter ; extra == "dev"
Requires-Dist: flit ; extra == "dev"
Requires-Dist: nox ; extra == "dev"
Requires-Dist: isort ; extra == "dev"
Requires-Dist: pytest ; extra == "dev"
Requires-Dist: pytest-cov ; extra == "dev"
Requires-Dist: pytest-xdist ; extra == "dev"
Requires-Dist: nox ; extra == "test"
Requires-Dist: pytest ; extra == "test"
Requires-Dist: pytest-cov ; extra == "test"
Requires-Dist: pytest-xdist ; extra == "test"
Project-URL: Home, https://github.com/metagentools/GraphBin2
Provides-Extra: dev
Provides-Extra: test
